{"format": "keras", "nodes": [{"name": "input_2", "id": "input_2", "class_name": "InputLayer", "output_shape": [null, 40, 200], "num_parameters": 0}, {"name": "bl_3", "id": "bl_3", "class_name": "BL", "output_shape": [null, 60, 10], "num_parameters": 5000}, {"name": "activation_4", "id": "activation_4", "class_name": "Activation", "output_shape": [null, 60, 10], "num_parameters": 0}, {"name": "dropout_3", "id": "dropout_3", "class_name": "Dropout", "output_shape": [null, 60, 10], "num_parameters": 0}, {"name": "bl_4", "id": "bl_4", "class_name": "BL", "output_shape": [null, 120, 5], "num_parameters": 7850}, {"name": "activation_5", "id": "activation_5", "class_name": "Activation", "output_shape": [null, 120, 5], "num_parameters": 0}, {"name": "dropout_4", "id": "dropout_4", "class_name": "Dropout", "output_shape": [null, 120, 5], "num_parameters": 0}, {"name": "tabl_2", "id": "tabl_2", "class_name": "TABL", "output_shape": [null, 3], "num_parameters": 394}, {"name": "activation_6", "id": "activation_6", "class_name": "Activation", "output_shape": [null, 3], "num_parameters": 0}], "edges": [["input_2", "bl_3"], ["bl_3", "activation_4"], ["activation_4", "dropout_3"], ["dropout_3", "bl_4"], ["bl_4", "activation_5"], ["activation_5", "dropout_4"], ["dropout_4", "tabl_2"], ["tabl_2", "activation_6"]]}